<?xml version="1.0" encoding="UTF-8"?>
<Form xmlns="http://v8.1c.ru/8.3/xcf/logform" xmlns:app="http://v8.1c.ru/8.2/managed-application/core" xmlns:cfg="http://v8.1c.ru/8.1/data/enterprise/current-config" xmlns:dcscor="http://v8.1c.ru/8.1/data-composition-system/core" xmlns:dcsset="http://v8.1c.ru/8.1/data-composition-system/settings" xmlns:ent="http://v8.1c.ru/8.1/data/enterprise" xmlns:lf="http://v8.1c.ru/8.2/managed-application/logform" xmlns:style="http://v8.1c.ru/8.1/data/ui/style" xmlns:sys="http://v8.1c.ru/8.1/data/ui/fonts/system" xmlns:v8="http://v8.1c.ru/8.1/data/core" xmlns:v8ui="http://v8.1c.ru/8.1/data/ui" xmlns:web="http://v8.1c.ru/8.1/data/ui/colors/web" xmlns:win="http://v8.1c.ru/8.1/data/ui/colors/windows" xmlns:xr="http://v8.1c.ru/8.3/xcf/readable" xmlns:xs="http://www.w3.org/2001/XMLSchema" xmlns:xsi="http://www.w3.org/2001/XMLSchema-instance" version="2.0">
	<Title>
		<v8:item>
			<v8:lang>en</v8:lang>
			<v8:content>Search for references</v8:content>
		</v8:item>
	</Title>
	<AutoTitle>false</AutoTitle>
	<CommandBarLocation>Top</CommandBarLocation>
	<ReportResult>Result</ReportResult>
	<DetailsData>DetailsData</DetailsData>
	<ReportFormType>Main</ReportFormType>
	<VariantAppearance>CurrentOptionDescription</VariantAppearance>
	<AutoShowState>Auto</AutoShowState>
	<CustomSettingsFolder xsi:type="xs:string">SettingsExtendedTooltip</CustomSettingsFolder>
	<AutoCommandBar name="FormCommandBar" id="-1">
		<Autofill>false</Autofill>
	</AutoCommandBar>
	<Events>
		<Event name="OnOpen">OnOpen</Event>
		<Event name="OnCreateAtServer">OnCreateAtServer</Event>
	</Events>
	<ChildItems>
		<UsualGroup name="OptionGroup" id="32">
			<Group>Horizontal</Group>
			<Representation>None</Representation>
			<ShowTitle>false</ShowTitle>
			<ExtendedTooltip name="OptionGroupExtendedTooltip" id="33"/>
			<ChildItems>
				<InputField name="CurrentOptionDescription" id="63">
					<DataPath>CurrentOptionDescription</DataPath>
					<ReadOnly>true</ReadOnly>
					<TitleLocation>Left</TitleLocation>
					<ContextMenu name="CurrentOptionDescriptionContextMenu" id="64"/>
					<ExtendedTooltip name="CurrentOptionDescriptionExtendedTooltip" id="65"/>
				</InputField>
				<Button name="SelectOptionButton" id="37">
					<Type>UsualButton</Type>
					<SkipOnInput>false</SkipOnInput>
					<CommandName>Form.StandardCommand.LoadVariant</CommandName>
					<Parameter xsi:nil="true"/>
					<ExtendedTooltip name="SelectOptionButtonExtendedTooltip" id="38"/>
				</Button>
			</ChildItems>
		</UsualGroup>
		<CommandBar name="MainCommandBar" id="39">
			<Title>
				<v8:item>
					<v8:lang>en</v8:lang>
					<v8:content>Main command bar</v8:content>
				</v8:item>
			</Title>
			<ToolTip>
				<v8:item>
					<v8:lang>en</v8:lang>
					<v8:content>Main command bar</v8:content>
				</v8:item>
			</ToolTip>
			<ExtendedTooltip name="MainCommandBarExtendedTooltip" id="40"/>
			<ChildItems>
				<Button name="GenerateReport" id="41">
					<Type>CommandBarButton</Type>
					<DefaultButton>true</DefaultButton>
					<SkipOnInput>false</SkipOnInput>
					<CommandName>Form.Command.Generate</CommandName>
					<Parameter xsi:nil="true"/>
					<ExtendedTooltip name="GenerateReportExtendedTooltip" id="42"/>
				</Button>
				<Button name="Settings" id="43">
					<Type>CommandBarButton</Type>
					<SkipOnInput>false</SkipOnInput>
					<CommandName>Form.StandardCommand.ReportSettings</CommandName>
					<Parameter xsi:nil="true"/>
					<ExtendedTooltip name="SettingsExtendedTooltip" id="44"/>
				</Button>
				<Button name="SelectSettingsItem" id="45">
					<Type>CommandBarButton</Type>
					<SkipOnInput>false</SkipOnInput>
					<OnlyInAllActions>false</OnlyInAllActions>
					<CommandName>Form.StandardCommand.LoadReportSettings</CommandName>
					<Parameter xsi:nil="true"/>
					<ExtendedTooltip name="SelectSettingsItemExtendedTooltip" id="46"/>
				</Button>
				<Button name="SaveSettings" id="47">
					<Type>CommandBarButton</Type>
					<SkipOnInput>false</SkipOnInput>
					<OnlyInAllActions>false</OnlyInAllActions>
					<CommandName>Form.StandardCommand.SaveReportSettings</CommandName>
					<Parameter xsi:nil="true"/>
					<ExtendedTooltip name="SaveSettingsExtendedTooltip" id="48"/>
				</Button>
				<Button name="StandardSettings" id="49">
					<Type>CommandBarButton</Type>
					<SkipOnInput>false</SkipOnInput>
					<OnlyInAllActions>false</OnlyInAllActions>
					<CommandName>Form.StandardCommand.StandardSettings</CommandName>
					<Parameter xsi:nil="true"/>
					<ExtendedTooltip name="StandardSettingsExtendedTooltip" id="50"/>
				</Button>
				<Button name="NewWindow" id="51">
					<Type>CommandBarButton</Type>
					<SkipOnInput>false</SkipOnInput>
					<OnlyInAllActions>false</OnlyInAllActions>
					<CommandName>Form.StandardCommand.NewWindow</CommandName>
					<Parameter xsi:nil="true"/>
					<ExtendedTooltip name="NewWindowExtendedTooltip" id="52"/>
				</Button>
				<Button name="ChangeOption" id="53">
					<Type>CommandBarButton</Type>
					<SkipOnInput>false</SkipOnInput>
					<OnlyInAllActions>false</OnlyInAllActions>
					<CommandName>Form.StandardCommand.ChangeVariant</CommandName>
					<Parameter xsi:nil="true"/>
					<ExtendedTooltip name="ChangeOptionExtendedTooltip" id="54"/>
				</Button>
				<Button name="SelectOption" id="55">
					<Type>CommandBarButton</Type>
					<SkipOnInput>false</SkipOnInput>
					<OnlyInAllActions>false</OnlyInAllActions>
					<CommandName>Form.StandardCommand.LoadVariant</CommandName>
					<Parameter xsi:nil="true"/>
					<ExtendedTooltip name="SelectOptionExtendedTooltip" id="56"/>
				</Button>
				<Button name="SaveOption" id="57">
					<Type>CommandBarButton</Type>
					<SkipOnInput>false</SkipOnInput>
					<OnlyInAllActions>false</OnlyInAllActions>
					<CommandName>Form.StandardCommand.SaveVariant</CommandName>
					<Parameter xsi:nil="true"/>
					<ExtendedTooltip name="SaveOptionExtendedTooltip" id="58"/>
				</Button>
				<Button name="CustomizeForm" id="59">
					<Type>CommandBarButton</Type>
					<SkipOnInput>false</SkipOnInput>
					<OnlyInAllActions>false</OnlyInAllActions>
					<CommandName>Form.StandardCommand.CustomizeForm</CommandName>
					<Parameter xsi:nil="true"/>
					<ExtendedTooltip name="CustomizeFormExtendedTooltip" id="60"/>
				</Button>
				<Button name="Help" id="61">
					<Type>CommandBarButton</Type>
					<SkipOnInput>false</SkipOnInput>
					<OnlyInAllActions>true</OnlyInAllActions>
					<CommandName>Form.StandardCommand.Help</CommandName>
					<Parameter xsi:nil="true"/>
					<ExtendedTooltip name="HelpExtendedTooltip" id="62"/>
				</Button>
			</ChildItems>
		</CommandBar>
		<SpreadSheetDocumentField name="Result" id="1">
			<DataPath>Result</DataPath>
			<TitleLocation>None</TitleLocation>
			<ContextMenu name="ResultContextMenu" id="2"/>
			<ExtendedTooltip name="ResultExtendedTooltip" id="3"/>
		</SpreadSheetDocumentField>
	</ChildItems>
	<Attributes>
		<Attribute name="Report" id="1">
			<Type>
				<v8:Type>cfg:ReportObject.SearchForReferences</v8:Type>
			</Type>
			<MainAttribute>true</MainAttribute>
		</Attribute>
		<Attribute name="DetailsData" id="3">
			<Type>
				<v8:Type>xs:string</v8:Type>
				<v8:StringQualifiers>
					<v8:Length>0</v8:Length>
					<v8:AllowedLength>Variable</v8:AllowedLength>
				</v8:StringQualifiers>
			</Type>
		</Attribute>
		<Attribute name="Result" id="4">
			<Title>
				<v8:item>
					<v8:lang>en</v8:lang>
					<v8:content>Result</v8:content>
				</v8:item>
			</Title>
			<Type>
				<v8:Type xmlns:mxl="http://v8.1c.ru/8.2/data/spreadsheet">mxl:SpreadsheetDocument</v8:Type>
			</Type>
		</Attribute>
		<Attribute name="CurrentOptionDescription" id="2">
			<Title>
				<v8:item>
					<v8:lang>en</v8:lang>
					<v8:content>Report option</v8:content>
				</v8:item>
			</Title>
			<Type>
				<v8:Type>xs:string</v8:Type>
				<v8:StringQualifiers>
					<v8:Length>0</v8:Length>
					<v8:AllowedLength>Variable</v8:AllowedLength>
				</v8:StringQualifiers>
			</Type>
		</Attribute>
	</Attributes>
	<Commands>
		<Command name="Generate" id="2">
			<Title>
				<v8:item>
					<v8:lang>en</v8:lang>
					<v8:content>Generate</v8:content>
				</v8:item>
			</Title>
			<ToolTip>
				<v8:item>
					<v8:lang>en</v8:lang>
					<v8:content>Generate</v8:content>
				</v8:item>
			</ToolTip>
			<Picture>
				<xr:Ref>StdPicture.GenerateReport</xr:Ref>
				<xr:LoadTransparent>true</xr:LoadTransparent>
			</Picture>
			<Action>Generate</Action>
			<Representation>TextPicture</Representation>
		</Command>
	</Commands>
	<Parameters>
		<Parameter name="ReferenceSet">
			<Type/>
		</Parameter>
	</Parameters>
</Form>